{
  "$schema": "https://mintlify.com/docs.json",
  "name": "CVA (Class Variance Authority)",
  "theme": "willow",
  "colors": {
    "primary": "#afafaf",
    "light": "#484848",
    "dark": "#2b2b2b"
  },
  "favicon": "https://media.brand.dev/d534404c-6843-49b1-a4b4-3ff5b471f76f.png",
  "logo": {
    "light": "https://media.brand.dev/699c40a3-f46c-4d58-9d98-b0b56e7cd3ca.jpg",
    "dark": "https://media.brand.dev/699c40a3-f46c-4d58-9d98-b0b56e7cd3ca.jpg"
  },
  "navbar": {
    "primary": {
      "type": "github",
      "href": "https://github.com/joe-bell/cva"
    }
  },
  "footer": {
    "socials": {
      "github": "https://github.com/joe-bell/cva"
    }
  },
  "navigation": {
    "tabs": [
      {
        "tab": "Documentation",
        "groups": [
          {
            "group": "Get Started",
            "pages": ["index", "getting-started/installation", "getting-started/quickstart"]
          },
          {
            "group": "Core Concepts",
            "pages": [
              "getting-started/variants",
              "getting-started/compound-variants",
              "getting-started/default-variants",
              "getting-started/composing-components",
              "getting-started/extending-components",
              "getting-started/typescript"
            ]
          },
          {
            "group": "Examples",
            "pages": [
              "examples/react",
              "examples/vue",
              "examples/svelte",
              "examples/astro",
              "examples/11ty",
              "examples/bem",
              "examples/other-use-cases"
            ]
          },
          {
            "group": "Help",
            "pages": ["faqs"]
          }
        ]
      },
      {
        "tab": "API Reference",
        "groups": [
          {
            "group": "API",
            "pages": [
              "api-reference/cva",
              "api-reference/cx",
              "api-reference/compose",
              "api-reference/define-config",
              "api-reference/variant-props"
            ]
          }
        ]
      }
    ]
  }
}
